gemini_audio_transcription/__init__.py
gemini_audio_transcription/aligner.py
gemini_audio_transcription/api_key_example.py
gemini_audio_transcription/processor.py
gemini_audio_transcription/transcriber.py
gemini_audio_transcription/version.py
gemini_audio_transcription-0.1.1.dist-info/licenses/LICENSE
gemini_audio_transcription-0.1.1.dist-info/METADATA
gemini_audio_transcription-0.1.1.dist-info/WHEEL
gemini_audio_transcription-0.1.1.dist-info/top_level.txt
gemini_audio_transcription-0.1.1.dist-info/RECORD
