Metadata-Version: 2.4
Name: gemini_audio_transcription
Version: 0.1.1
Summary: Audio transcription and alignment library using Google Gemini API for TTS labeling
Home-page: https://github.com/manhcuong17072002/AudioTranscription
Author: Manh Cuong
Author-email: manhcuong17072002@gmail.com
License: MIT
Project-URL: Bug Reports, https://github.com/manhcuong17072002/AudioTranscription/issues
Project-URL: Source, https://github.com/manhcuong17072002/AudioTranscription
Project-URL: Documentation, https://github.com/manhcuong17072002/AudioTranscription/blob/main/README.md
Keywords: audio,transcription,alignment,gemini,tts,whisper,stable-ts
Classifier: Development Status :: 4 - Beta
Classifier: Intended Audience :: Developers
Classifier: Intended Audience :: Science/Research
Classifier: Programming Language :: Python :: 3
Classifier: Programming Language :: Python :: 3.10
Classifier: Programming Language :: Python :: 3.11
Classifier: License :: OSI Approved :: MIT License
Classifier: Operating System :: OS Independent
Classifier: Topic :: Scientific/Engineering :: Artificial Intelligence
Classifier: Topic :: Multimedia :: Sound/Audio :: Speech
Requires-Python: >=3.10
License-File: LICENSE
Requires-Dist: google-genai==1.10.0
Requires-Dist: pydub
Requires-Dist: python-magic
Requires-Dist: stable-ts==2.19.0
Requires-Dist: torch==2.6.0
Requires-Dist: torchaudio==2.6.0
Provides-Extra: demo
Requires-Dist: plotly; extra == "demo"
Requires-Dist: streamlit; extra == "demo"
Provides-Extra: dev
Requires-Dist: pytest; extra == "dev"
Requires-Dist: black; extra == "dev"
Requires-Dist: flake8; extra == "dev"
Dynamic: author
Dynamic: author-email
Dynamic: classifier
Dynamic: description
Dynamic: description-content-type
Dynamic: home-page
Dynamic: keywords
Dynamic: license
Dynamic: license-file
Dynamic: project-url
Dynamic: provides-extra
Dynamic: requires-dist
Dynamic: requires-python
Dynamic: summary
